jerryc05/__init__.py
jerryc05/__main__.py
jerryc05/mod_12306/__init__.py
jerryc05/mod_12306/__main__.py
jerryc05/mod_12306/mod_parser.py
jerryc05/mod_12306/station_name.py
jerryc05-0.1.6.dist-info/METADATA
jerryc05-0.1.6.dist-info/WHEEL
jerryc05-0.1.6.dist-info/entry_points.txt
jerryc05-0.1.6.dist-info/top_level.txt
jerryc05-0.1.6.dist-info/zip-safe
jerryc05-0.1.6.dist-info/RECORD
